README.md
pyproject.toml
setup.py
gp_wrapper/__init__.py
gp_wrapper.egg-info/PKG-INFO
gp_wrapper.egg-info/SOURCES.txt
gp_wrapper.egg-info/dependency_links.txt
gp_wrapper.egg-info/requires.txt
gp_wrapper.egg-info/top_level.txt
gp_wrapper/objects/Album.py
gp_wrapper/objects/MediaItem.py
gp_wrapper/objects/__init__.py
gp_wrapper/objects/core/__init__.py
gp_wrapper/objects/core/album.py
gp_wrapper/objects/core/enrichment_item.py
gp_wrapper/objects/core/gp.py
gp_wrapper/objects/core/media_item/__init__.py
gp_wrapper/objects/core/media_item/core_media_item.py
gp_wrapper/objects/core/media_item/filters/__init__.py
gp_wrapper/objects/core/media_item/filters/content_filter.py
gp_wrapper/objects/core/media_item/filters/date_filter.py
gp_wrapper/objects/core/media_item/filters/feature_filter.py
gp_wrapper/objects/core/media_item/filters/media_type_filter.py
gp_wrapper/objects/core/media_item/filters/search_filter.py
gp_wrapper/utils/__init__.py
gp_wrapper/utils/helpers.py
gp_wrapper/utils/pbar.py
gp_wrapper/utils/win32_ctime.py
gp_wrapper/utils/structures/__init__.py
gp_wrapper/utils/structures/data_types.py
gp_wrapper/utils/structures/enums.py
gp_wrapper/utils/structures/parent_classes.py