Metadata-Version: 2.1
Name: gp-wrapper
Version: 0.9.8
Summary: A Google Photos API wrapper library
Home-page: https://github.com/danielnachumdev/gp_wrapper
Author: danielnachumdev
Author-email: danielnachumdev <danielnachumdev@gmail.com>
Project-URL: Homepage, https://github.com/danielnachumdev/gp_wrapper
Project-URL: Bug Tracker, https://github.com/danielnachumdev/gp_wrapper/issues
Keywords: functions,methods,classes,API
Classifier: Development Status :: 3 - Alpha
Classifier: Intended Audience :: Developers
Classifier: Programming Language :: Python :: 3
Classifier: Operating System :: Microsoft :: Windows
Requires-Python: >=3.8.0
